{
  "kind": "collectionType",
  "collectionName": "points",
  "info": {
    "singularName": "point",
    "pluralName": "points",
    "displayName": "Points",
    "description": ""
  },
  "options": {
    "draftAndPublish": true
  },
  "pluginOptions": {
    "i18n": {
      "localized": true
    }
  },
  "attributes": {
    "title": {
      "pluginOptions": {
        "i18n": {
          "localized": true
        }
      },
      "type": "string",
      "required": true,
      "maxLength": 500
    },
    "intro": {
      "pluginOptions": {
        "i18n": {
          "localized": true
        }
      },
      "type": "text",
      "required": false,
      "maxLength": 1000
    },
    "description": {
      "pluginOptions": {
        "i18n": {
          "localized": true
        }
      },
      "type": "richtext",
      "required": true
    },
    "category": {
      "pluginOptions": {
        "i18n": {
          "localized": false
        }
      },
      "type": "enumeration",
      "enum": [
        "entertainment",
        "event",
        "attraction",
        "nightMarket",
        "hypermarket",
        "beach",
        "restaurant",
        "cafe",
        "marina",
        "police",
        "gasStation",
        "carRental",
        "hotel"
      ],
      "required": true
    },
    "logo": {
      "type": "media",
      "multiple": false,
      "required": false,
      "allowedTypes": [
        "images"
      ],
      "pluginOptions": {
        "i18n": {
          "localized": false
        }
      }
    },
    "lat": {
      "pluginOptions": {
        "i18n": {
          "localized": false
        }
      },
      "type": "float",
      "required": true
    },
    "lng": {
      "pluginOptions": {
        "i18n": {
          "localized": false
        }
      },
      "type": "float",
      "required": true
    },
    "uuid": {
      "pluginOptions": {
        "i18n": {
          "localized": false
        }
      },
      "type": "string",
      "maxLength": 40
    },
    "address": {
      "pluginOptions": {
        "i18n": {
          "localized": true
        }
      },
      "type": "string",
      "maxLength": 500
    },
    "web": {
      "pluginOptions": {
        "i18n": {
          "localized": true
        }
      },
      "type": "string"
    }
  }
}
